fastapi_cloud_tasks/__init__.py
fastapi_cloud_tasks/decorators.py
fastapi_cloud_tasks/delayed_route.py
fastapi_cloud_tasks/delayer.py
fastapi_cloud_tasks/dependencies.py
fastapi_cloud_tasks/exception.py
fastapi_cloud_tasks/hooks.py
fastapi_cloud_tasks/requester.py
fastapi_cloud_tasks/scheduled_route.py
fastapi_cloud_tasks/scheduler.py
fastapi_cloud_tasks/utils.py
fastapi_cloud_tasks-0.1.2.dist-info/LICENSE
fastapi_cloud_tasks-0.1.2.dist-info/METADATA
fastapi_cloud_tasks-0.1.2.dist-info/WHEEL
fastapi_cloud_tasks-0.1.2.dist-info/top_level.txt
fastapi_cloud_tasks-0.1.2.dist-info/RECORD
