Metadata-Version: 2.1
Name: fastapi-cloud-tasks
Version: 0.1.2
Summary: Trigger delayed Cloud Tasks from FastAPI
License-File: LICENSE
Requires-Dist: google-cloud-tasks
Requires-Dist: google-cloud-scheduler
Requires-Dist: fastapi
